ocr_sycophant/__init__.py
ocr_sycophant/cli.py
ocr_sycophant/encoder.py
ocr_sycophant/model.py
ocr_sycophant/utils.py
OCR_Sycophant-0.0.4.dist-info/METADATA
OCR_Sycophant-0.0.4.dist-info/WHEEL
OCR_Sycophant-0.0.4.dist-info/entry_points.txt
OCR_Sycophant-0.0.4.dist-info/top_level.txt
OCR_Sycophant-0.0.4.dist-info/RECORD
